DAQData.py
DAQData-2.5.dist-info/LICENSE
DAQData-2.5.dist-info/METADATA
DAQData-2.5.dist-info/WHEEL
DAQData-2.5.dist-info/top_level.txt
DAQData-2.5.dist-info/RECORD
