Metadata-Version: 2.1
Name: DAQData
Version: 2.5
Summary: Read and plot slow and fast data binary files from centrifuge experiments conducted at Center of Geotechnical Modeling at University of California Davis
Home-page: https://github.com/SumeetSinha/DAQData
Author: Sumeet Kumar Sinha
Author-email: sumeet.kumar507@gmail.com
License: UNKNOWN
Keywords: Centrifuge,Center of Geotechnical MOdeling,CGM,UC Davis,Binary Data
Platform: UNKNOWN
Classifier: Intended Audience :: Science/Research
Classifier: Topic :: Scientific/Engineering
Classifier: Programming Language :: Python :: 2
Classifier: Programming Language :: Python :: 3
Classifier: License :: OSI Approved :: MIT License
Classifier: Operating System :: OS Independent
Requires-Python: >=2
Requires-Dist: matplotlib
Requires-Dist: pandas
